rs_audio_stats-1.4.1.dist-info/METADATA
rs_audio_stats-1.4.1.dist-info/WHEEL
rs_audio_stats/__init__.py
rs_audio_stats/_rs_audio_stats.cp311-win_amd64.pyd
rs_audio_stats-1.4.1.dist-info/RECORD
