Metadata-Version: 2.4
Name: rs_audio_stats
Version: 1.4.1
Classifier: Development Status :: 5 - Production/Stable
Classifier: Intended Audience :: Developers
Classifier: License :: OSI Approved :: MIT License
Classifier: Programming Language :: Python :: 3
Classifier: Programming Language :: Python :: 3.10
Classifier: Programming Language :: Python :: 3.11
Classifier: Programming Language :: Python :: 3.12
Classifier: Programming Language :: Rust
Classifier: Topic :: Multimedia :: Sound/Audio :: Analysis
Summary: High-performance audio analysis library with EBU R128 loudness measurement, powered by Rust
Keywords: audio,loudness,ebu-r128,analysis,normalization
Home-Page: https://pypi.org/project/rs-audio-stats/
Author: Hiroshi Tamura
Requires-Python: >=3.10, <3.13
Project-URL: Homepage, https://pypi.org/project/rs-audio-stats/
Project-URL: Documentation, https://github.com/hiroshi-tamura/rs_audio_stats/blob/main/lib_python/API_REFERENCE_JP.md
Project-URL: GitHub, https://github.com/hiroshi-tamura/rs_audio_stats
